{"v":"5.9.0","fr":24,"ip":0,"op":48,"w":390,"h":846,"nm":"Comp 1","ddd":0,"assets":[],"layers":[{"ddd":0,"ind":5,"ty":4,"nm":"round_light","sr":1,"ks":{"o":{"a":0,"k":100,"ix":11},"r":{"a":1,"k":[{"i":{"x":[0.794],"y":[0.771]},"o":{"x":[0.167],"y":[0.182]},"t":0,"s":[0]},{"t":48,"s":[180]}],"ix":10},"p":{"a":0,"k":[195.15,422.997,0],"ix":2,"l":2},"a":{"a":0,"k":[-3.686,-194.204,0],"ix":1,"l":2},"s":{"a":0,"k":[100,100,100],"ix":6,"l":2}},"ao":0,"shapes":[{"ty":"gr","it":[{"d":1,"ty":"el","s":{"a":0,"k":[122.6,122.6],"ix":2},"p":{"a":0,"k":[0,0],"ix":3},"nm":"Ellipse Path 1","mn":"ADBE Vector Shape - Ellipse","hd":false},{"ty":"gs","o":{"a":0,"k":100,"ix":9},"w":{"a":0,"k":120,"ix":10},"g":{"p":3,"k":{"a":0,"k":[0,1,0.878,0.235,0.675,1,0.908,0.424,1,1,0.937,0.612,0,1,0.651,0.5,1,0],"ix":8}},"s":{"a":0,"k":[0,0],"ix":4},"e":{"a":0,"k":[100,0],"ix":5},"t":2,"h":{"a":0,"k":0,"ix":6},"a":{"a":0,"k":0,"ix":7},"lc":1,"lj":1,"ml":1,"ml2":{"a":0,"k":1,"ix":13},"bm":0,"d":[{"n":"d","nm":"dash","v":{"a":0,"k":24,"ix":1}},{"n":"o","nm":"offset","v":{"a":0,"k":0,"ix":7}}],"nm":"Gradient Stroke 1","mn":"ADBE Vector Graphic - G-Stroke","hd":false},{"ty":"tr","p":{"a":0,"k":[-3.619,-194.07],"ix":2},"a":{"a":0,"k":[0,0],"ix":1},"s":{"a":0,"k":[156.594,160.065],"ix":3},"r":{"a":0,"k":0,"ix":6},"o":{"a":0,"k":100,"ix":7},"sk":{"a":0,"k":0,"ix":4},"sa":{"a":0,"k":0,"ix":5},"nm":"Transform"}],"nm":"Ellipse 1","np":2,"cix":2,"bm":0,"ix":1,"mn":"ADBE Vector Group","hd":false}],"ip":0,"op":120,"st":0,"bm":0}],"markers":[]}